odoo/addons/stock_location_address/README.rst
odoo/addons/stock_location_address/__init__.py
odoo/addons/stock_location_address/__manifest__.py
odoo/addons/stock_location_address/i18n/it.po
odoo/addons/stock_location_address/i18n/stock_location_address.pot
odoo/addons/stock_location_address/models/__init__.py
odoo/addons/stock_location_address/models/stock_location.py
odoo/addons/stock_location_address/readme/CONTRIBUTORS.md
odoo/addons/stock_location_address/readme/DESCRIPTION.md
odoo/addons/stock_location_address/readme/USAGE.md
odoo/addons/stock_location_address/static/description/icon.png
odoo/addons/stock_location_address/static/description/index.html
odoo/addons/stock_location_address/tests/__init__.py
odoo/addons/stock_location_address/tests/test_location_address.py
odoo/addons/stock_location_address/views/stock_location_views.xml
odoo_addon_stock_location_address-18.0.1.0.0.2.dist-info/METADATA
odoo_addon_stock_location_address-18.0.1.0.0.2.dist-info/WHEEL
odoo_addon_stock_location_address-18.0.1.0.0.2.dist-info/top_level.txt
odoo_addon_stock_location_address-18.0.1.0.0.2.dist-info/RECORD
